plunge/__init__.py
plunge/main.py
plunge-0.0.8.dist-info/METADATA
plunge-0.0.8.dist-info/WHEEL
plunge-0.0.8.dist-info/licenses/LICENSE
plunge-0.0.8.dist-info/RECORD
